README.txt
setup.cfg
setup.py
jwt_based_authentication/__init__.py
jwt_based_authentication/admin.py
jwt_based_authentication/apps.py
jwt_based_authentication/models.py
jwt_based_authentication/serializers.py
jwt_based_authentication/tests.py
jwt_based_authentication/urls.py
jwt_based_authentication/views.py
jwt_based_authentication/migrations/__init__.py
jwtauthapi.egg-info/PKG-INFO
jwtauthapi.egg-info/SOURCES.txt
jwtauthapi.egg-info/dependency_links.txt
jwtauthapi.egg-info/top_level.txt